{
    "version": "6.8",
    "url": "https://joytokey.net/download/JoyToKey.zip",
    "##": "バージョンチェックと自動アップデート",
    "hash": "7d79efe6000587c5a07842cb6ec47601c583c128e47c64327307eb3fdb6e3bc3",
    "depends": "sudo",
    "bin": "JoyToKey.exe",
    "shortcuts": [
        [
            "JoyToKey.exe",
            "JoyToKey"
        ]
    ],
    "checkver": {
        "url": "https://joytokey.net/",
        "re": "JoyToKey ([\\d.]+) "
    },
    "autoupdate": {
        "url": "https://joytokey.net/download/JoyToKey.zip"
    }
}
