{
    "homepage": "https://moonlight-stream.org",
    "version": "4.0.0",
    "architecture": {
        "32bit": {
            "url": "https://github.com/moonlight-stream/moonlight-qt/releases/download/v4.0.0/MoonlightPortable-x86-4.0.0.zip",
            "hash": "61f6ff003b8ad8ee8fb4554d5657f96a81bffb6cd710893acd68fbb97707d612"
        },
        "64bit": {
            "url": "https://github.com/moonlight-stream/moonlight-qt/releases/download/v4.0.0/MoonlightPortable-x64-4.0.0.zip",
            "hash": "777474754746bf77e2d9305ac576e5850063dec48d0807e9e642aa47ff153657"
        }
    },
    "depends": "sudo",
    "bin": "Moonlight.exe",
    "shortcuts": [
        [
            "Moonlight.exe",
            "Moonlight PC"
        ]
    ],
    "checkver": {
        "github": "https://github.com/moonlight-stream/moonlight-qt"
    },
    "autoupdate": {
        "architecture": {
            "32bit": {
                "url": "https://github.com/moonlight-stream/moonlight-qt/releases/download/v$version/MoonlightPortable-x86-$version.zip"
            },
            "64bit": {
                "url": "https://github.com/moonlight-stream/moonlight-qt/releases/download/v$version/MoonlightPortable-x64-$version.zip"
            }
        }
    }
}
